resource_segmentation/__init__.py
resource_segmentation/group.py
resource_segmentation/segment.py
resource_segmentation/splitter.py
resource_segmentation/stream.py
resource_segmentation/truncation.py
resource_segmentation/types.py
resource_segmentation-0.0.7.dist-info/LICENSE
resource_segmentation-0.0.7.dist-info/METADATA
resource_segmentation-0.0.7.dist-info/WHEEL
resource_segmentation-0.0.7.dist-info/RECORD
