Metadata-Version: 2.3
Name: resource-segmentation
Version: 0.0.7
Summary: 
License: MIT
Author: Tao Zeyu
Author-email: i@taozeyu.com
Maintainer: Tao Zeyu
Maintainer-email: i@taozeyu.com
Requires-Python: >=3.11,<3.14
Classifier: Development Status :: 2 - Pre-Alpha
Classifier: Intended Audience :: Developers
Classifier: License :: OSI Approved :: MIT License
Classifier: Programming Language :: Python
Classifier: Programming Language :: Python :: 3
Classifier: Programming Language :: Python :: 3.11
Classifier: Programming Language :: Python :: 3.12
Classifier: Programming Language :: Python :: 3.13
Project-URL: Homepage, https://github.com/Moskize91/resource-segmentation
Project-URL: Repository, https://github.com/Moskize91/resource-segmentation
